{
  "latest": "2026-07-24",
  "reports": [
    {
      "date": "2026-07-24",
      "title": "No defined-risk option setup cleared the publication gate",
      "edition": "Daily market edition",
      "dataAsOfUtc": "2026-07-24T08:58:46.211Z",
      "topSymbol": "Cash",
      "ideaCount": 0,
      "topScore": 0
    },
    {
      "date": "2026-07-22",
      "title": "No defined-risk option setup cleared the publication gate",
      "edition": "Daily market edition",
      "dataAsOfUtc": "2026-07-22T15:47:58.836Z",
      "topSymbol": "Cash",
      "ideaCount": 0,
      "topScore": 0
    },
    {
      "date": "2026-07-21",
      "title": "1 defined-risk option setups lead the Jul 21, 2026 board",
      "edition": "Daily market edition",
      "dataAsOfUtc": "2026-07-21T16:00:53.418Z",
      "topSymbol": "TLT",
      "ideaCount": 1,
      "topScore": 85.18
    },
    {
      "date": "2026-07-20",
      "title": "No defined-risk option setup cleared the publication gate",
      "edition": "Daily market edition",
      "dataAsOfUtc": "2026-07-20T16:18:34.553Z",
      "topSymbol": "Cash",
      "ideaCount": 0,
      "topScore": 0
    },
    {
      "date": "2026-07-17",
      "title": "1 defined-risk option setups lead the Jul 17, 2026 board",
      "edition": "Daily market edition",
      "dataAsOfUtc": "2026-07-17T16:07:39.010Z",
      "topSymbol": "QQQ",
      "ideaCount": 1,
      "topScore": 78.63
    },
    {
      "date": "2026-07-16",
      "title": "2 defined-risk option setups lead the Jul 16, 2026 board",
      "edition": "Daily market edition",
      "dataAsOfUtc": "2026-07-16T17:41:09.660Z",
      "topSymbol": "TLT",
      "ideaCount": 2,
      "topScore": 93.61
    },
    {
      "date": "2026-07-15",
      "title": "No defined-risk option setup cleared the publication gate",
      "edition": "Daily market edition",
      "dataAsOfUtc": "2026-07-15T16:59:37.104Z",
      "topSymbol": "Cash",
      "ideaCount": 0,
      "topScore": 0
    },
    {
      "date": "2026-07-14",
      "title": "5 defined-risk option setups lead the Jul 14, 2026 board",
      "edition": "Daily market edition",
      "dataAsOfUtc": "2026-07-14T16:06:57.451Z",
      "topSymbol": "TLT",
      "ideaCount": 5,
      "topScore": 61.86
    },
    {
      "date": "2026-07-13",
      "title": "5 defined-risk option setups lead the Jul 13, 2026 board",
      "edition": "Daily market edition",
      "dataAsOfUtc": "2026-07-13T15:31:38.463Z",
      "topSymbol": "BAC",
      "ideaCount": 5,
      "topScore": 49.91
    },
    {
      "date": "2026-07-10",
      "title": "5 defined-risk option setups lead the Jul 10, 2026 board",
      "edition": "Daily market edition",
      "dataAsOfUtc": "2026-07-11T10:38:06.683Z",
      "topSymbol": "NFLX",
      "ideaCount": 5,
      "topScore": 52.76
    },
    {
      "date": "2026-06-19",
      "title": "5 defined-risk option setups lead the Jun 19, 2026 board",
      "edition": "Historical calibration edition",
      "dataAsOfUtc": "2026-06-19T15:45:00.000Z",
      "topSymbol": "MARA",
      "ideaCount": 5,
      "topScore": 55.7
    }
  ]
}
