{
  "schemaVersion": "1.0",
  "reportId": "rfdelta-options-2026-07-13-7b17cb1f399a",
  "runMetadata": {
    "reportDate": "2026-07-13",
    "marketSessionDate": "2026-07-13",
    "generatedAtUtc": "2026-07-13T15:23:55.806Z",
    "dataAsOfUtc": "2026-07-13T15:23:50.977Z",
    "edition": "Daily market edition",
    "methodologyVersion": "rfdelta-options-v2",
    "selectionHash": "7b17cb1f399a48a6966a8a9f77fe0aed7571ac43eb142c58eee54111c6905f0c",
    "datasetRunId": "run-3d3c3f4f58060547",
    "featureVersion": "rfdelta-market-features-v1",
    "selectionPolicyVersion": "rfdelta-online-policy-v1",
    "trainingSampleCount": 5
  },
  "executiveSummary": {
    "headline": "3 defined-risk option setups lead the Jul 13, 2026 board",
    "standfirst": "NFLX 7/24 78/80 Call Credit Spread ranks first with a 51.79 score, 68.0% modeled probability of profit and $145.00 maximum one-lot risk. The basket balances 1 bullish and 2 bearish expressions.",
    "marketCommentary": [
      "The option board is not rewarding indiscriminate beta. Across the published names, the mean five-session move is +0.1%, while 0 setups carry realized volatility above 65%. That combination favors defined-risk structures and hard entry limits over naked premium exposure.",
      "The screen quotes 105 liquid underlyings and requests 40 option chains through its core, mover, volume and rotation sleeves. It accepts only same-session chains with two usable legs, then forces every idea through the same conservative mark: pay the ask for the long option and receive the bid for the short. The resulting ranking is intentionally harsher than a midpoint screen, because a trade that only works at a theoretical fill is not a durable public idea.",
      "Direction comes from five- and twenty-session price structure rather than a headline guess. That keeps the daily board responsive to what is actually trading while the scenario engine still reserves room for jumps, volatility expansion and path-dependent failure. The result is a short list, not a promise that every liquid ticker deserves a trade."
    ],
    "selectionCommentary": [
      "NFLX wins the top slot because liquidity, directional alignment and bounded payoff reinforce one another. Its credit entry of 0.55 creates 0.38 dollars of maximum reward for each dollar of maximum risk, with breakeven at $78.55.",
      "IWM supplies the counterweight. Its put debit structure scores 40.57 and carries $81.00 of one-lot maximum loss. The basket is therefore ranked as a portfolio of explicit risks, not as five unrelated ticker calls."
    ],
    "riskCommentary": "The basket's maximum losses are additive if every thesis fails. Quote slippage, early assignment and volatility repricing can also change the practical outcome before expiration, so the published entry is a ceiling for debits and a floor for credits, not an assurance of execution."
  },
  "marketContext": {
    "providerAttribution": "RFDELTA normalized U.S. equity and options market data",
    "universeCount": 105,
    "quotedSymbolCount": 105,
    "chainSymbolCount": 40,
    "includedSymbolCount": 38,
    "excludedSymbolCount": 37,
    "candidateCount": 30,
    "bullishCandidateCount": 21,
    "bearishCandidateCount": 9,
    "regimeCounts": {
      "risk_off": 4,
      "mean_reversion": 22,
      "risk_on": 2,
      "trend": 1,
      "vol_expansion": 1
    }
  },
  "analytics": {
    "publishedIdeaCount": 3,
    "topScore": 51.79,
    "averageProbabilityProfit": 0.5674666666666667,
    "totalExpectedValueDollars": -8.42,
    "totalMaxLossDollars": 297,
    "totalMaxProfitDollars": 203,
    "debitIdeaCount": 1,
    "creditIdeaCount": 2
  },
  "topTrades": [
    {
      "rank": 1,
      "id": "nflx-2026-07-24-call_credit-80-78",
      "name": "NFLX 7/24 78/80 Call Credit Spread",
      "symbol": "NFLX",
      "underlyingMark": 74.7799,
      "expiration": "2026-07-24",
      "daysToExpiry": 11,
      "structureType": "Credit",
      "style": "call_credit",
      "direction": "bearish",
      "theme": "technology and AI leadership",
      "regime": "risk_off",
      "correlationBucket": "large-cap-growth",
      "bucket": "watchlist",
      "entry": 0.55,
      "width": 2,
      "maxLossDollars": 145,
      "maxProfitDollars": 55,
      "rewardToRisk": 0.38,
      "breakeven": 78.55,
      "requiredMovePctToBreakeven": 5.04,
      "probabilityProfit": 0.68,
      "probabilityNearMaxProfit": 0.6589,
      "expectedValueDollars": -5.58,
      "blackScholesEdge": -0.0499,
      "impliedVolUsed": 0.6598,
      "liquidityScore": 0.9755,
      "score": 51.79,
      "riskFlags": [],
      "thesis": "NFLX is expressing a bearish risk off setup: -1.6% over five sessions and -8.0% over twenty, with +42.8% annualized realized volatility. The call credit contains the thesis to a defined one-lot loss while preserving a measurable payoff through 7/24.",
      "longLeg": {
        "optionSymbol": "NFLX  260724C00080000",
        "right": "C",
        "strike": 80,
        "bid": 1.55,
        "ask": 1.57,
        "mid": 1.56,
        "volume": 2633,
        "openInterest": 14296,
        "quoteTimeUtc": "2026-07-13T15:22:38.352Z"
      },
      "shortLeg": {
        "optionSymbol": "NFLX  260724C00078000",
        "right": "C",
        "strike": 78,
        "bid": 2.12,
        "ask": 2.15,
        "mid": 2.135,
        "volume": 275,
        "openInterest": 1615,
        "quoteTimeUtc": "2026-07-13T15:22:38.386Z"
      },
      "sourceAsOfUtc": "2026-07-13T15:23:50.977Z",
      "marketEvidence": [
        "Underlying $75 at the source timestamp",
        "-1.6% over five sessions and -8.0% over twenty, with +42.8% annualized realized volatility.",
        "2908 contracts of combined session volume and 15911 contracts of combined open interest across the two legs"
      ],
      "historySessionCount": 260,
      "advancedMetrics": {
        "symbol": "NFLX",
        "historySessions": 260,
        "historyConfidence": 1,
        "return1d": 0.019216,
        "return5d": -0.016313,
        "return20d": -0.079858,
        "sma5Distance": -0.00397,
        "sma20Distance": -0.006742,
        "emaTrend": -0.019139,
        "macdPct": 0.007121,
        "rsi14": 54.856629,
        "atr14Pct": 0.035687,
        "bollingerZ20": -0.174924,
        "realizedVol5": 0.271723,
        "realizedVol20": 0.428038,
        "downsideVol20": 0.271408,
        "maxDrawdown20": -0.131872,
        "trendEfficiency20": 0.206363,
        "volumeZScore20": -1.940826,
        "atmImpliedVol": 0.651437,
        "putCallIvSkew": -0.014389,
        "putCallVolumeRatio": 0.222962,
        "putCallOpenInterestRatio": 0.425589,
        "expectedMovePct": 0.090265,
        "meanQuoteWidthPct": 4.46296,
        "liquidContractRatio": 0.875,
        "trendSignal": -0.515888,
        "riskAdjustedMomentum": -0.746274
      },
      "trainingAdjustment": 0,
      "trainingPolicyVersion": "rfdelta-online-policy-v1",
      "fiveDayReturn": -0.016313,
      "twentyDayReturn": -0.079858,
      "realizedVolatility": 0.428038,
      "lessonAdjustments": [],
      "commentary": {
        "convictionLabel": "Actionable watch",
        "rankingRead": "The setup scores 51.79 on the common scale, supported by 68.0% modeled probability of profit, 0.98 liquidity quality and a conservative modeled expectancy of -$5.58, which keeps sizing discipline central.",
        "setup": "NFLX enters with -1.6% five-session momentum and -8.0% over twenty sessions. Realized volatility is 42.8%, placing the underlying in a risk off regime. The bearish structure expresses that tape without allowing the loss to expand beyond the spread debit or defined credit width.",
        "execution": "Buy the 80 call and sell the 78 call, both expiring Jul 24, 2026. The credit mark of 0.55 assumes the long ask and short bid, not a midpoint. Do not accept less than 0.55 of credit without rerunning the payoff.",
        "risk": "Maximum one-lot loss is $145.00. Breakeven is $78.55 and sits 5.0% above the source mark, providing an upside cushion. Primary watch: a directional break before expiration. A break in the stated directional regime invalidates the reason for holding even when the contractual maximum loss remains unchanged.",
        "payoffRead": "Maximum one-lot profit is $55.00, or 0.38 times maximum risk. The simulation assigns 65.9% probability to finishing near maximum profit and uses 66.0% implied volatility across deterministic jump-stress paths."
      },
      "underlyingChart": {
        "assetPath": "/charts/2026-07-13/underlying/01-nflx.svg",
        "entryDate": "2026-07-13",
        "entryPrice": 74.7799,
        "points": [
          {
            "date": "2026-03-04",
            "close": 98.66
          },
          {
            "date": "2026-03-05",
            "close": 99.17
          },
          {
            "date": "2026-03-06",
            "close": 99.02
          },
          {
            "date": "2026-03-09",
            "close": 98.32
          },
          {
            "date": "2026-03-10",
            "close": 96.94
          },
          {
            "date": "2026-03-11",
            "close": 94.89
          },
          {
            "date": "2026-03-12",
            "close": 94.31
          },
          {
            "date": "2026-03-13",
            "close": 95.31
          },
          {
            "date": "2026-03-16",
            "close": 95.2
          },
          {
            "date": "2026-03-17",
            "close": 94.36
          },
          {
            "date": "2026-03-18",
            "close": 94.7
          },
          {
            "date": "2026-03-19",
            "close": 91.74
          },
          {
            "date": "2026-03-20",
            "close": 91.82
          },
          {
            "date": "2026-03-23",
            "close": 93.38
          },
          {
            "date": "2026-03-24",
            "close": 90.92
          },
          {
            "date": "2026-03-25",
            "close": 92.28
          },
          {
            "date": "2026-03-26",
            "close": 93.32
          },
          {
            "date": "2026-03-27",
            "close": 93.43
          },
          {
            "date": "2026-03-30",
            "close": 92.97
          },
          {
            "date": "2026-03-31",
            "close": 96.15
          },
          {
            "date": "2026-04-01",
            "close": 95.55
          },
          {
            "date": "2026-04-02",
            "close": 98.66
          },
          {
            "date": "2026-04-06",
            "close": 98.93
          },
          {
            "date": "2026-04-07",
            "close": 98.82
          },
          {
            "date": "2026-04-08",
            "close": 99.39
          },
          {
            "date": "2026-04-09",
            "close": 102.05
          },
          {
            "date": "2026-04-10",
            "close": 103.01
          },
          {
            "date": "2026-04-13",
            "close": 103.16
          },
          {
            "date": "2026-04-14",
            "close": 106.28
          },
          {
            "date": "2026-04-15",
            "close": 107.71
          },
          {
            "date": "2026-04-16",
            "close": 107.79
          },
          {
            "date": "2026-04-17",
            "close": 97.31
          },
          {
            "date": "2026-04-20",
            "close": 94.83
          },
          {
            "date": "2026-04-21",
            "close": 92.58
          },
          {
            "date": "2026-04-22",
            "close": 93.24
          },
          {
            "date": "2026-04-23",
            "close": 92.82
          },
          {
            "date": "2026-04-24",
            "close": 92.44
          },
          {
            "date": "2026-04-27",
            "close": 91.37
          },
          {
            "date": "2026-04-28",
            "close": 92.27
          },
          {
            "date": "2026-04-29",
            "close": 92.12
          },
          {
            "date": "2026-04-30",
            "close": 93.61
          },
          {
            "date": "2026-05-01",
            "close": 92.06
          },
          {
            "date": "2026-05-04",
            "close": 91.02
          },
          {
            "date": "2026-05-05",
            "close": 87.89
          },
          {
            "date": "2026-05-06",
            "close": 88.27
          },
          {
            "date": "2026-05-07",
            "close": 88.25
          },
          {
            "date": "2026-05-08",
            "close": 87.49
          },
          {
            "date": "2026-05-11",
            "close": 85.45
          },
          {
            "date": "2026-05-12",
            "close": 87.66
          },
          {
            "date": "2026-05-13",
            "close": 87.56
          },
          {
            "date": "2026-05-14",
            "close": 86.94
          },
          {
            "date": "2026-05-15",
            "close": 87.02
          },
          {
            "date": "2026-05-18",
            "close": 89.65
          },
          {
            "date": "2026-05-19",
            "close": 89.33
          },
          {
            "date": "2026-05-20",
            "close": 88.09
          },
          {
            "date": "2026-05-21",
            "close": 89.3
          },
          {
            "date": "2026-05-22",
            "close": 88.6
          },
          {
            "date": "2026-05-26",
            "close": 87.68
          },
          {
            "date": "2026-05-27",
            "close": 87.35
          },
          {
            "date": "2026-05-28",
            "close": 86.36
          },
          {
            "date": "2026-05-29",
            "close": 86.02
          },
          {
            "date": "2026-06-01",
            "close": 85.85
          },
          {
            "date": "2026-06-02",
            "close": 83.33
          },
          {
            "date": "2026-06-03",
            "close": 81.52
          },
          {
            "date": "2026-06-04",
            "close": 81.56
          },
          {
            "date": "2026-06-05",
            "close": 82.18
          },
          {
            "date": "2026-06-08",
            "close": 82.64
          },
          {
            "date": "2026-06-09",
            "close": 81.41
          },
          {
            "date": "2026-06-10",
            "close": 82
          },
          {
            "date": "2026-06-11",
            "close": 81.27
          },
          {
            "date": "2026-06-12",
            "close": 80.34
          },
          {
            "date": "2026-06-15",
            "close": 81.67
          },
          {
            "date": "2026-06-16",
            "close": 78.72
          },
          {
            "date": "2026-06-17",
            "close": 76.96
          },
          {
            "date": "2026-06-18",
            "close": 77.38
          },
          {
            "date": "2026-06-22",
            "close": 72.88
          },
          {
            "date": "2026-06-23",
            "close": 72.82
          },
          {
            "date": "2026-06-24",
            "close": 71.84
          },
          {
            "date": "2026-06-25",
            "close": 70.9
          },
          {
            "date": "2026-06-26",
            "close": 73.81
          },
          {
            "date": "2026-06-29",
            "close": 73.78
          },
          {
            "date": "2026-06-30",
            "close": 71.4
          },
          {
            "date": "2026-07-01",
            "close": 74.19
          },
          {
            "date": "2026-07-02",
            "close": 77.65
          },
          {
            "date": "2026-07-06",
            "close": 76.02
          },
          {
            "date": "2026-07-07",
            "close": 76.18
          },
          {
            "date": "2026-07-08",
            "close": 75.59
          },
          {
            "date": "2026-07-09",
            "close": 75.47
          },
          {
            "date": "2026-07-10",
            "close": 73.37
          },
          {
            "date": "2026-07-13",
            "close": 74.7799
          }
        ]
      }
    },
    {
      "rank": 2,
      "id": "iwm-2026-07-24-put_debit-294-292",
      "name": "IWM 7/24 294/292 Put Debit Spread",
      "symbol": "IWM",
      "underlyingMark": 294.26,
      "expiration": "2026-07-24",
      "daysToExpiry": 11,
      "structureType": "Debit",
      "style": "put_debit",
      "direction": "bearish",
      "theme": "small-cap breadth",
      "regime": "mean_reversion",
      "correlationBucket": "broad-market",
      "bucket": "conditional",
      "entry": 0.81,
      "width": 2,
      "maxLossDollars": 81,
      "maxProfitDollars": 119,
      "rewardToRisk": 1.47,
      "breakeven": 293.19,
      "requiredMovePctToBreakeven": -0.36,
      "probabilityProfit": 0.4474,
      "probabilityNearMaxProfit": 0.4003,
      "expectedValueDollars": 6.96,
      "blackScholesEdge": 0.0667,
      "impliedVolUsed": 0.1908,
      "liquidityScore": 0.9184,
      "score": 40.57,
      "riskFlags": [],
      "thesis": "IWM is expressing a bearish mean reversion setup: -1.6% over five sessions and +1.3% over twenty, with +13.4% annualized realized volatility. The put debit contains the thesis to a defined one-lot loss while preserving a measurable payoff through 7/24.",
      "longLeg": {
        "optionSymbol": "IWM   260724P00294000",
        "right": "P",
        "strike": 294,
        "bid": 3.48,
        "ask": 3.53,
        "mid": 3.505,
        "volume": 887,
        "openInterest": 4368,
        "quoteTimeUtc": "2026-07-13T15:22:32.884Z"
      },
      "shortLeg": {
        "optionSymbol": "IWM   260724P00292000",
        "right": "P",
        "strike": 292,
        "bid": 2.72,
        "ask": 2.77,
        "mid": 2.745,
        "volume": 25,
        "openInterest": 469,
        "quoteTimeUtc": "2026-07-13T15:22:33.633Z"
      },
      "sourceAsOfUtc": "2026-07-13T15:23:50.977Z",
      "marketEvidence": [
        "Underlying $294 at the source timestamp",
        "-1.6% over five sessions and +1.3% over twenty, with +13.4% annualized realized volatility.",
        "912 contracts of combined session volume and 4837 contracts of combined open interest across the two legs"
      ],
      "historySessionCount": 260,
      "advancedMetrics": {
        "symbol": "IWM",
        "historySessions": 260,
        "historyConfidence": 1,
        "return1d": -0.005845,
        "return5d": -0.015524,
        "return20d": 0.013257,
        "sma5Distance": -0.003967,
        "sma20Distance": -0.00696,
        "emaTrend": 0.002346,
        "macdPct": -0.003116,
        "rsi14": 42.478893,
        "atr14Pct": 0.015447,
        "bollingerZ20": -0.728264,
        "realizedVol5": 0.144769,
        "realizedVol20": 0.133886,
        "downsideVol20": 0.039726,
        "maxDrawdown20": -0.023199,
        "trendEfficiency20": 0.088812,
        "volumeZScore20": -2.275706,
        "atmImpliedVol": 0.185494,
        "putCallIvSkew": 0.014989,
        "putCallVolumeRatio": 1.804757,
        "putCallOpenInterestRatio": 2.243214,
        "expectedMovePct": 0.025726,
        "meanQuoteWidthPct": 2.492857,
        "liquidContractRatio": 0.875,
        "trendSignal": -0.13371,
        "riskAdjustedMomentum": 0.353523
      },
      "trainingAdjustment": 0,
      "trainingPolicyVersion": "rfdelta-online-policy-v1",
      "fiveDayReturn": -0.015524,
      "twentyDayReturn": 0.013257,
      "realizedVolatility": 0.133886,
      "lessonAdjustments": [],
      "commentary": {
        "convictionLabel": "Trigger-dependent setup",
        "rankingRead": "The setup scores 40.57 on the common scale, supported by 44.7% modeled probability of profit, 0.92 liquidity quality and positive modeled expectancy of $6.96.",
        "setup": "IWM enters with -1.6% five-session momentum and +1.3% over twenty sessions. Realized volatility is 13.4%, placing the underlying in a mean reversion regime. The bearish structure expresses that tape without allowing the loss to expand beyond the spread debit or defined credit width.",
        "execution": "Buy the 294 put and sell the 292 put, both expiring Jul 24, 2026. The debit mark of 0.81 assumes the long ask and short bid, not a midpoint. Do not pay more than 0.81 for the spread without rerunning the payoff.",
        "risk": "Maximum one-lot loss is $81.00. Breakeven is $293.19 and requires a 0.4% decline from the source mark. Primary watch: a directional break before expiration. A break in the stated directional regime invalidates the reason for holding even when the contractual maximum loss remains unchanged.",
        "payoffRead": "Maximum one-lot profit is $119.00, or 1.47 times maximum risk. The simulation assigns 40.0% probability to finishing near maximum profit and uses 19.1% implied volatility across deterministic jump-stress paths."
      },
      "underlyingChart": {
        "assetPath": "/charts/2026-07-13/underlying/02-iwm.svg",
        "entryDate": "2026-07-13",
        "entryPrice": 294.26,
        "points": [
          {
            "date": "2026-03-04",
            "close": 261.76
          },
          {
            "date": "2026-03-05",
            "close": 256.76
          },
          {
            "date": "2026-03-06",
            "close": 250.89
          },
          {
            "date": "2026-03-09",
            "close": 253.62
          },
          {
            "date": "2026-03-10",
            "close": 253.36
          },
          {
            "date": "2026-03-11",
            "close": 252.85
          },
          {
            "date": "2026-03-12",
            "close": 247.41
          },
          {
            "date": "2026-03-13",
            "close": 246.59
          },
          {
            "date": "2026-03-16",
            "close": 248.92
          },
          {
            "date": "2026-03-17",
            "close": 250.05
          },
          {
            "date": "2026-03-18",
            "close": 246.02
          },
          {
            "date": "2026-03-19",
            "close": 247.63
          },
          {
            "date": "2026-03-20",
            "close": 242.22
          },
          {
            "date": "2026-03-23",
            "close": 247.45
          },
          {
            "date": "2026-03-24",
            "close": 248.78
          },
          {
            "date": "2026-03-25",
            "close": 251.82
          },
          {
            "date": "2026-03-26",
            "close": 247.44
          },
          {
            "date": "2026-03-27",
            "close": 243.1
          },
          {
            "date": "2026-03-30",
            "close": 239.61
          },
          {
            "date": "2026-03-31",
            "close": 248
          },
          {
            "date": "2026-04-01",
            "close": 249.56
          },
          {
            "date": "2026-04-02",
            "close": 251.29
          },
          {
            "date": "2026-04-06",
            "close": 252.36
          },
          {
            "date": "2026-04-07",
            "close": 252.91
          },
          {
            "date": "2026-04-08",
            "close": 260.47
          },
          {
            "date": "2026-04-09",
            "close": 261.96
          },
          {
            "date": "2026-04-10",
            "close": 261.3
          },
          {
            "date": "2026-04-13",
            "close": 265.07
          },
          {
            "date": "2026-04-14",
            "close": 268.72
          },
          {
            "date": "2026-04-15",
            "close": 269.39
          },
          {
            "date": "2026-04-16",
            "close": 269.95
          },
          {
            "date": "2026-04-17",
            "close": 275.78
          },
          {
            "date": "2026-04-20",
            "close": 277.35
          },
          {
            "date": "2026-04-21",
            "close": 274.51
          },
          {
            "date": "2026-04-22",
            "close": 276.48
          },
          {
            "date": "2026-04-23",
            "close": 275.52
          },
          {
            "date": "2026-04-24",
            "close": 276.65
          },
          {
            "date": "2026-04-27",
            "close": 277.14
          },
          {
            "date": "2026-04-28",
            "close": 273.91
          },
          {
            "date": "2026-04-29",
            "close": 272.08
          },
          {
            "date": "2026-04-30",
            "close": 277.97
          },
          {
            "date": "2026-05-01",
            "close": 279.28
          },
          {
            "date": "2026-05-04",
            "close": 277.88
          },
          {
            "date": "2026-05-05",
            "close": 282.56
          },
          {
            "date": "2026-05-06",
            "close": 286.8
          },
          {
            "date": "2026-05-07",
            "close": 282.26
          },
          {
            "date": "2026-05-08",
            "close": 284.17
          },
          {
            "date": "2026-05-11",
            "close": 285.33
          },
          {
            "date": "2026-05-12",
            "close": 282.57
          },
          {
            "date": "2026-05-13",
            "close": 282.67
          },
          {
            "date": "2026-05-14",
            "close": 284.45
          },
          {
            "date": "2026-05-15",
            "close": 277.6
          },
          {
            "date": "2026-05-18",
            "close": 275.97
          },
          {
            "date": "2026-05-19",
            "close": 273
          },
          {
            "date": "2026-05-20",
            "close": 279.87
          },
          {
            "date": "2026-05-21",
            "close": 282.49
          },
          {
            "date": "2026-05-22",
            "close": 285.12
          },
          {
            "date": "2026-05-26",
            "close": 290.51
          },
          {
            "date": "2026-05-27",
            "close": 290.37
          },
          {
            "date": "2026-05-28",
            "close": 292.03
          },
          {
            "date": "2026-05-29",
            "close": 290.43
          },
          {
            "date": "2026-06-01",
            "close": 288.98
          },
          {
            "date": "2026-06-02",
            "close": 291.66
          },
          {
            "date": "2026-06-03",
            "close": 287.67
          },
          {
            "date": "2026-06-04",
            "close": 292.01
          },
          {
            "date": "2026-06-05",
            "close": 281.65
          },
          {
            "date": "2026-06-08",
            "close": 284.11
          },
          {
            "date": "2026-06-09",
            "close": 285.02
          },
          {
            "date": "2026-06-10",
            "close": 282.05
          },
          {
            "date": "2026-06-11",
            "close": 290.41
          },
          {
            "date": "2026-06-12",
            "close": 292.95
          },
          {
            "date": "2026-06-15",
            "close": 294.64
          },
          {
            "date": "2026-06-16",
            "close": 292.08
          },
          {
            "date": "2026-06-17",
            "close": 289.88
          },
          {
            "date": "2026-06-18",
            "close": 295.59
          },
          {
            "date": "2026-06-22",
            "close": 298.18
          },
          {
            "date": "2026-06-23",
            "close": 295.32
          },
          {
            "date": "2026-06-24",
            "close": 296.69
          },
          {
            "date": "2026-06-25",
            "close": 298.91
          },
          {
            "date": "2026-06-26",
            "close": 299.83
          },
          {
            "date": "2026-06-29",
            "close": 298.97
          },
          {
            "date": "2026-06-30",
            "close": 300.45
          },
          {
            "date": "2026-07-01",
            "close": 299.32
          },
          {
            "date": "2026-07-02",
            "close": 297.58
          },
          {
            "date": "2026-07-06",
            "close": 298.9
          },
          {
            "date": "2026-07-07",
            "close": 296.19
          },
          {
            "date": "2026-07-08",
            "close": 293.48
          },
          {
            "date": "2026-07-09",
            "close": 297.24
          },
          {
            "date": "2026-07-10",
            "close": 295.99
          },
          {
            "date": "2026-07-13",
            "close": 294.26
          }
        ]
      }
    },
    {
      "rank": 3,
      "id": "cmcsa-2026-07-24-put_credit-23-24",
      "name": "CMCSA 7/24 24/23 Put Credit Spread",
      "symbol": "CMCSA",
      "underlyingMark": 24.185,
      "expiration": "2026-07-24",
      "daysToExpiry": 11,
      "structureType": "Credit",
      "style": "put_credit",
      "direction": "bullish",
      "theme": "consumer and communications demand",
      "regime": "risk_on",
      "correlationBucket": "consumer",
      "bucket": "conditional",
      "entry": 0.29,
      "width": 1,
      "maxLossDollars": 71,
      "maxProfitDollars": 29,
      "rewardToRisk": 0.41,
      "breakeven": 23.71,
      "requiredMovePctToBreakeven": -1.96,
      "probabilityProfit": 0.575,
      "probabilityNearMaxProfit": 0.5229,
      "expectedValueDollars": -9.8,
      "blackScholesEdge": -0.0968,
      "impliedVolUsed": 0.5202,
      "liquidityScore": 0.6578,
      "score": 38.24,
      "riskFlags": [
        "negative conservative BS edge"
      ],
      "thesis": "CMCSA is expressing a bullish risk on setup: +3.4% over five sessions and +0.9% over twenty, with +33.5% annualized realized volatility. The put credit contains the thesis to a defined one-lot loss while preserving a measurable payoff through 7/24.",
      "longLeg": {
        "optionSymbol": "CMCSA 260724P00023000",
        "right": "P",
        "strike": 23,
        "bid": 0.36,
        "ask": 0.43,
        "mid": 0.395,
        "volume": 1,
        "openInterest": 1327,
        "quoteTimeUtc": "2026-07-13T15:21:49.094Z"
      },
      "shortLeg": {
        "optionSymbol": "CMCSA 260724P00024000",
        "right": "P",
        "strike": 24,
        "bid": 0.72,
        "ask": 0.76,
        "mid": 0.74,
        "volume": 64,
        "openInterest": 631,
        "quoteTimeUtc": "2026-07-13T15:21:56.786Z"
      },
      "sourceAsOfUtc": "2026-07-13T15:23:50.977Z",
      "marketEvidence": [
        "Underlying $24 at the source timestamp",
        "+3.4% over five sessions and +0.9% over twenty, with +33.5% annualized realized volatility.",
        "65 contracts of combined session volume and 1958 contracts of combined open interest across the two legs"
      ],
      "historySessionCount": 260,
      "advancedMetrics": {
        "symbol": "CMCSA",
        "historySessions": 260,
        "historyConfidence": 1,
        "return1d": 0.026093,
        "return5d": 0.034431,
        "return20d": 0.00897,
        "sma5Distance": 0.027357,
        "sma20Distance": 0.033006,
        "emaTrend": 0.001937,
        "macdPct": 0.006315,
        "rsi14": 68.338247,
        "atr14Pct": 0.037019,
        "bollingerZ20": 1.14503,
        "realizedVol5": 0.203958,
        "realizedVol20": 0.335298,
        "downsideVol20": 0.200089,
        "maxDrawdown20": -0.08898,
        "trendEfficiency20": 0.027582,
        "volumeZScore20": -1.298784,
        "atmImpliedVol": 0.516316,
        "putCallIvSkew": 0.024123,
        "putCallVolumeRatio": 0.665698,
        "putCallOpenInterestRatio": 0.488343,
        "expectedMovePct": 0.071532,
        "meanQuoteWidthPct": 54.685662,
        "liquidContractRatio": 0.229167,
        "trendSignal": 0.382647,
        "riskAdjustedMomentum": 0.107004
      },
      "trainingAdjustment": 0,
      "trainingPolicyVersion": "rfdelta-online-policy-v1",
      "fiveDayReturn": 0.034431,
      "twentyDayReturn": 0.00897,
      "realizedVolatility": 0.335298,
      "lessonAdjustments": [],
      "commentary": {
        "convictionLabel": "Trigger-dependent setup",
        "rankingRead": "The setup scores 38.24 on the common scale, supported by 57.5% modeled probability of profit, 0.66 liquidity quality and a conservative modeled expectancy of -$9.80, which keeps sizing discipline central.",
        "setup": "CMCSA enters with +3.4% five-session momentum and +0.9% over twenty sessions. Realized volatility is 33.5%, placing the underlying in a risk on regime. The bullish structure expresses that tape without allowing the loss to expand beyond the spread debit or defined credit width.",
        "execution": "Buy the 23 put and sell the 24 put, both expiring Jul 24, 2026. The credit mark of 0.29 assumes the long ask and short bid, not a midpoint. Do not accept less than 0.29 of credit without rerunning the payoff.",
        "risk": "Maximum one-lot loss is $71.00. Breakeven is $23.71 and sits 2.0% below the source mark, providing a downside cushion. Primary watch: negative conservative BS edge. A break in the stated directional regime invalidates the reason for holding even when the contractual maximum loss remains unchanged.",
        "payoffRead": "Maximum one-lot profit is $29.00, or 0.41 times maximum risk. The simulation assigns 52.3% probability to finishing near maximum profit and uses 52.0% implied volatility across deterministic jump-stress paths."
      },
      "underlyingChart": {
        "assetPath": "/charts/2026-07-13/underlying/03-cmcsa.svg",
        "entryDate": "2026-07-13",
        "entryPrice": 24.185,
        "points": [
          {
            "date": "2026-03-04",
            "close": 32.09
          },
          {
            "date": "2026-03-05",
            "close": 31.6
          },
          {
            "date": "2026-03-06",
            "close": 31.91
          },
          {
            "date": "2026-03-09",
            "close": 31.04
          },
          {
            "date": "2026-03-10",
            "close": 31.07
          },
          {
            "date": "2026-03-11",
            "close": 30.57
          },
          {
            "date": "2026-03-12",
            "close": 30.16
          },
          {
            "date": "2026-03-13",
            "close": 30.16
          },
          {
            "date": "2026-03-16",
            "close": 30.34
          },
          {
            "date": "2026-03-17",
            "close": 30.08
          },
          {
            "date": "2026-03-18",
            "close": 28.57
          },
          {
            "date": "2026-03-19",
            "close": 28.98
          },
          {
            "date": "2026-03-20",
            "close": 29.02
          },
          {
            "date": "2026-03-23",
            "close": 29.01
          },
          {
            "date": "2026-03-24",
            "close": 29.22
          },
          {
            "date": "2026-03-25",
            "close": 28.73
          },
          {
            "date": "2026-03-26",
            "close": 28.72
          },
          {
            "date": "2026-03-27",
            "close": 28.33
          },
          {
            "date": "2026-03-30",
            "close": 28.9
          },
          {
            "date": "2026-03-31",
            "close": 28.71
          },
          {
            "date": "2026-04-01",
            "close": 28.05
          },
          {
            "date": "2026-04-02",
            "close": 27.93
          },
          {
            "date": "2026-04-06",
            "close": 27.66
          },
          {
            "date": "2026-04-07",
            "close": 27.79
          },
          {
            "date": "2026-04-08",
            "close": 27.96
          },
          {
            "date": "2026-04-09",
            "close": 28.31
          },
          {
            "date": "2026-04-10",
            "close": 27.93
          },
          {
            "date": "2026-04-13",
            "close": 28.05
          },
          {
            "date": "2026-04-14",
            "close": 28.14
          },
          {
            "date": "2026-04-15",
            "close": 28.3
          },
          {
            "date": "2026-04-16",
            "close": 29.35
          },
          {
            "date": "2026-04-17",
            "close": 29.63
          },
          {
            "date": "2026-04-20",
            "close": 29.73
          },
          {
            "date": "2026-04-21",
            "close": 29.05
          },
          {
            "date": "2026-04-22",
            "close": 29.37
          },
          {
            "date": "2026-04-23",
            "close": 31.64
          },
          {
            "date": "2026-04-24",
            "close": 27.56
          },
          {
            "date": "2026-04-27",
            "close": 27.51
          },
          {
            "date": "2026-04-28",
            "close": 27.64
          },
          {
            "date": "2026-04-29",
            "close": 26.76
          },
          {
            "date": "2026-04-30",
            "close": 27.04
          },
          {
            "date": "2026-05-01",
            "close": 27.19
          },
          {
            "date": "2026-05-04",
            "close": 27.07
          },
          {
            "date": "2026-05-05",
            "close": 26.46
          },
          {
            "date": "2026-05-06",
            "close": 26.44
          },
          {
            "date": "2026-05-07",
            "close": 26.24
          },
          {
            "date": "2026-05-08",
            "close": 25.4
          },
          {
            "date": "2026-05-11",
            "close": 25.03
          },
          {
            "date": "2026-05-12",
            "close": 24.9
          },
          {
            "date": "2026-05-13",
            "close": 24.94
          },
          {
            "date": "2026-05-14",
            "close": 25.17
          },
          {
            "date": "2026-05-15",
            "close": 24.76
          },
          {
            "date": "2026-05-18",
            "close": 24.93
          },
          {
            "date": "2026-05-19",
            "close": 24.8
          },
          {
            "date": "2026-05-20",
            "close": 24.88
          },
          {
            "date": "2026-05-21",
            "close": 25.08
          },
          {
            "date": "2026-05-22",
            "close": 25.21
          },
          {
            "date": "2026-05-26",
            "close": 25.15
          },
          {
            "date": "2026-05-27",
            "close": 25.22
          },
          {
            "date": "2026-05-28",
            "close": 25.16
          },
          {
            "date": "2026-05-29",
            "close": 24.87
          },
          {
            "date": "2026-06-01",
            "close": 25.05
          },
          {
            "date": "2026-06-02",
            "close": 24.85
          },
          {
            "date": "2026-06-03",
            "close": 23.52
          },
          {
            "date": "2026-06-04",
            "close": 23.33
          },
          {
            "date": "2026-06-05",
            "close": 23.82
          },
          {
            "date": "2026-06-08",
            "close": 23.76
          },
          {
            "date": "2026-06-09",
            "close": 23.85
          },
          {
            "date": "2026-06-10",
            "close": 23.97
          },
          {
            "date": "2026-06-11",
            "close": 23.97
          },
          {
            "date": "2026-06-12",
            "close": 24.5
          },
          {
            "date": "2026-06-15",
            "close": 23.97
          },
          {
            "date": "2026-06-16",
            "close": 23.66
          },
          {
            "date": "2026-06-17",
            "close": 22.69
          },
          {
            "date": "2026-06-18",
            "close": 22.43
          },
          {
            "date": "2026-06-22",
            "close": 22.32
          },
          {
            "date": "2026-06-23",
            "close": 22.8
          },
          {
            "date": "2026-06-24",
            "close": 22.64
          },
          {
            "date": "2026-06-25",
            "close": 22.69
          },
          {
            "date": "2026-06-26",
            "close": 23.17
          },
          {
            "date": "2026-06-29",
            "close": 24.22
          },
          {
            "date": "2026-06-30",
            "close": 24.55
          },
          {
            "date": "2026-07-01",
            "close": 23.73
          },
          {
            "date": "2026-07-02",
            "close": 23.79
          },
          {
            "date": "2026-07-06",
            "close": 23.38
          },
          {
            "date": "2026-07-07",
            "close": 23.41
          },
          {
            "date": "2026-07-08",
            "close": 23.19
          },
          {
            "date": "2026-07-09",
            "close": 23.35
          },
          {
            "date": "2026-07-10",
            "close": 23.57
          },
          {
            "date": "2026-07-13",
            "close": 24.185
          }
        ]
      }
    }
  ],
  "accountability": {
    "sourceReportDate": "2026-07-10",
    "evaluatedThrough": "2026-07-13",
    "wins": 0,
    "losses": 0,
    "nearBreakeven": 0,
    "open": 5,
    "resolvedPnlDollars": 0,
    "read": "The Jul 10, 2026 basket has no scored expiration result yet. 5 positions remain open.",
    "trades": [
      {
        "tradeId": "nflx-2026-07-24-call_credit-77-76",
        "name": "NFLX 7/24 76/77 Call Credit Spread",
        "symbol": "NFLX",
        "style": "call_credit",
        "expiration": "2026-07-24",
        "status": "open",
        "read": "The spread remains open through Jul 24, 2026; no expiration result is assigned."
      },
      {
        "tradeId": "t-2026-07-24-call_credit-22-21.5",
        "name": "T 7/24 21.5/22 Call Credit Spread",
        "symbol": "T",
        "style": "call_credit",
        "expiration": "2026-07-24",
        "status": "open",
        "read": "The spread remains open through Jul 24, 2026; no expiration result is assigned."
      },
      {
        "tradeId": "wfc-2026-07-24-put_credit-84-85",
        "name": "WFC 7/24 85/84 Put Credit Spread",
        "symbol": "WFC",
        "style": "put_credit",
        "expiration": "2026-07-24",
        "status": "open",
        "read": "The spread remains open through Jul 24, 2026; no expiration result is assigned."
      },
      {
        "tradeId": "tlt-2026-07-24-put_debit-85-84.5",
        "name": "TLT 7/24 85/84.5 Put Debit Spread",
        "symbol": "TLT",
        "style": "put_debit",
        "expiration": "2026-07-24",
        "status": "open",
        "read": "The spread remains open through Jul 24, 2026; no expiration result is assigned."
      },
      {
        "tradeId": "pltr-2026-07-24-put_debit-125-120",
        "name": "PLTR 7/24 125/120 Put Debit Spread",
        "symbol": "PLTR",
        "style": "put_debit",
        "expiration": "2026-07-24",
        "status": "open",
        "read": "The spread remains open through Jul 24, 2026; no expiration result is assigned."
      }
    ]
  },
  "methodology": {
    "selectionCriteria": [
      "A broad liquid-symbol quote universe is intersected with the source's fingerprinted universe. Core market anchors, the largest percentage movers, the most active names and a date-seeded rotation sleeve determine which option chains are evaluated.",
      "The nearest expiration inside the configured 7-to-35-day window is chosen by distance from a 14-day target.",
      "Each candidate is a two-leg, one-lot vertical spread with a known maximum loss at entry.",
      "Both legs must clear bid, ask, open-interest, volume or depth, and relative quote-width gates.",
      "Momentum direction determines whether bullish call-debit and put-credit structures or bearish put-debit and call-credit structures enter the ranking set.",
      "Resolved trades train bounded feature adjustments only after the minimum sample threshold; every policy and input dataset is versioned with the report."
    ],
    "rankingFramework": [
      "Modeled probability of profit: 26% of the base score.",
      "Conservative expected-value efficiency: 22%.",
      "Two-leg liquidity quality: 18%.",
      "Maximum reward relative to maximum risk: 14%.",
      "Black-Scholes spread edge and directional signal strength: 10% each.",
      "Resolved prior outcomes adjust the strategy-style posterior without changing the underlying quote record.",
      "The advanced feature layer contributes at most 8 score points and currently contains 5 fully resolved training examples."
    ],
    "executionAssumption": "Every entry is marked conservatively: the long leg is bought at its ask and the short leg is sold at its bid. Maximum loss and maximum profit are shown for one spread before commissions, fees, early assignment and exercise costs.",
    "publicationCadence": "The weekday edition is selected at 10:45 a.m. Eastern. Official underlying closes extend each open-position chart after the regular session, and expiration results are added only after a finalized close is available.",
    "marketDataStatement": "RFDELTA normalized U.S. equity and options market data. Historical technical series: Yahoo Finance public daily chart history. Data timestamp: Jul 13, 2026, 11:23 AM EDT. Historical calibration editions are clearly labeled and are never promoted as current market data.",
    "disclaimer": "RFDELTA Top Option Trades is market intelligence, not individualized investment advice. Options can expire worthless, spreads can be assigned early, and displayed quotes may move before an order can be filled."
  }
}
