{
  "schemaVersion": "1.0",
  "featureVersion": "rfdelta-market-features-v1",
  "reportDate": "2026-07-13",
  "dataAsOfUtc": "2026-07-13T14:58:49.010Z",
  "sourceFingerprint": "3651e804e112f85ea6f306f656272e04eead212ea0fc51db2c8fcf539a80193d",
  "historicalData": {
    "provider": "Yahoo Finance",
    "dataset": "Public daily chart history",
    "queryStartDate": "2025-06-08",
    "queryEndDate": "2026-07-13",
    "requestedSymbolCount": 38,
    "hydratedSymbolCount": 38,
    "totalBarCount": 9880,
    "coverageRatio": 1
  },
  "chainSelection": {
    "strategyVersion": "rfdelta-chain-preselection-v1",
    "quoteUniverseCount": 105,
    "selectedSymbolCount": 40,
    "core": [
      "SPY",
      "QQQ",
      "IWM",
      "DIA",
      "TLT",
      "GLD",
      "XLE",
      "XLK",
      "SMH"
    ],
    "movers": [
      "APP",
      "LRCX",
      "INTC",
      "CRM",
      "MU",
      "ON",
      "USO",
      "ORCL",
      "NOW",
      "KLAC",
      "NUE",
      "AMAT",
      "HAL",
      "XOM",
      "ADBE",
      "SLV",
      "TXN",
      "AMD"
    ],
    "volume": [
      "NVDA",
      "AAPL",
      "NFLX",
      "TSLA",
      "PFE",
      "XLF",
      "PLTR"
    ],
    "rotation": [
      "BAC",
      "OXY",
      "COIN",
      "WFC",
      "MS",
      "NKE"
    ],
    "selectedSymbols": [
      "AAPL",
      "ADBE",
      "AMAT",
      "AMD",
      "APP",
      "BAC",
      "COIN",
      "CRM",
      "DIA",
      "GLD",
      "HAL",
      "INTC",
      "IWM",
      "KLAC",
      "LRCX",
      "MS",
      "MU",
      "NFLX",
      "NKE",
      "NOW",
      "NUE",
      "NVDA",
      "ON",
      "ORCL",
      "OXY",
      "PFE",
      "PLTR",
      "QQQ",
      "SLV",
      "SMH",
      "SPY",
      "TLT",
      "TSLA",
      "TXN",
      "USO",
      "WFC",
      "XLE",
      "XLF",
      "XLK",
      "XOM"
    ]
  },
  "symbols": [
    {
      "symbol": "AAPL",
      "historySessions": 260,
      "historyConfidence": 1,
      "return1d": 0.009831,
      "return5d": 0.018423,
      "return20d": 0.07709,
      "sma5Distance": 0.011493,
      "sma20Distance": 0.064087,
      "emaTrend": 0.034624,
      "macdPct": 0.008628,
      "rsi14": 64.271419,
      "atr14Pct": 0.027925,
      "bollingerZ20": 1.548579,
      "realizedVol5": 0.121866,
      "realizedVol20": 0.352354,
      "downsideVol20": 0.301421,
      "maxDrawdown20": -0.080504,
      "trendEfficiency20": 0.242524,
      "volumeZScore20": -0.966717,
      "atmImpliedVol": 0.24225,
      "putCallIvSkew": 0.019355,
      "putCallVolumeRatio": 3.184492,
      "putCallOpenInterestRatio": 0,
      "expectedMovePct": 0.038,
      "meanQuoteWidthPct": 79.948761,
      "liquidContractRatio": 0,
      "trendSignal": 0.629076,
      "riskAdjustedMomentum": 0.875137
    },
    {
      "symbol": "ADBE",
      "historySessions": 260,
      "historyConfidence": 1,
      "return1d": 0.028483,
      "return5d": 0.054753,
      "return20d": 0.051234,
      "sma5Distance": 0.02795,
      "sma20Distance": 0.102325,
      "emaTrend": 0.024523,
      "macdPct": 0.017968,
      "rsi14": 84.783093,
      "atr14Pct": 0.034042,
      "bollingerZ20": 1.85372,
      "realizedVol5": 0.187186,
      "realizedVol20": 0.440566,
      "downsideVol20": 0.401801,
      "maxDrawdown20": -0.116042,
      "trendEfficiency20": 0.138446,
      "volumeZScore20": -1.364916,
      "atmImpliedVol": 0.45942,
      "putCallIvSkew": -0.00669,
      "putCallVolumeRatio": 1.276289,
      "putCallOpenInterestRatio": 0.265655,
      "expectedMovePct": 0.063584,
      "meanQuoteWidthPct": 25.839986,
      "liquidContractRatio": 0.270833,
      "trendSignal": 0.640715,
      "riskAdjustedMomentum": 0.465165
    },
    {
      "symbol": "AMAT",
      "historySessions": 260,
      "historyConfidence": 1,
      "return1d": -0.032133,
      "return5d": -0.016279,
      "return20d": 0.05519,
      "sma5Distance": 0.005657,
      "sma20Distance": -0.044412,
      "emaTrend": 0.003952,
      "macdPct": -0.021119,
      "rsi14": 44.403454,
      "atr14Pct": 0.090145,
      "bollingerZ20": -0.60676,
      "realizedVol5": 0.701119,
      "realizedVol20": 0.978571,
      "downsideVol20": 0.488729,
      "maxDrawdown20": -0.233057,
      "trendEfficiency20": 0.048241,
      "volumeZScore20": -2.017748,
      "atmImpliedVol": 0.954833,
      "putCallIvSkew": -0.004908,
      "putCallVolumeRatio": 0.303571,
      "putCallOpenInterestRatio": 1.562059,
      "expectedMovePct": 0.131958,
      "meanQuoteWidthPct": 14.786311,
      "liquidContractRatio": 0.1875,
      "trendSignal": 0.066557,
      "riskAdjustedMomentum": 0.225593
    },
    {
      "symbol": "AMD",
      "historySessions": 260,
      "historyConfidence": 1,
      "return1d": -0.026098,
      "return5d": -0.015796,
      "return20d": 0.112355,
      "sma5Distance": 0.013123,
      "sma20Distance": 0.018049,
      "emaTrend": 0.027383,
      "macdPct": -0.005534,
      "rsi14": 48.637735,
      "atr14Pct": 0.069327,
      "bollingerZ20": 0.501264,
      "realizedVol5": 0.737437,
      "realizedVol20": 0.779807,
      "downsideVol20": 0.436152,
      "maxDrawdown20": -0.111549,
      "trendEfficiency20": 0.122566,
      "volumeZScore20": -2.432191,
      "atmImpliedVol": 0.771656,
      "putCallIvSkew": -0.015648,
      "putCallVolumeRatio": 0.29,
      "putCallOpenInterestRatio": 0,
      "expectedMovePct": 0.120553,
      "meanQuoteWidthPct": 22.226632,
      "liquidContractRatio": 0,
      "trendSignal": 0.240652,
      "riskAdjustedMomentum": 0.576324
    },
    {
      "symbol": "APP",
      "historySessions": 260,
      "historyConfidence": 1,
      "return1d": -0.102016,
      "return5d": -0.162802,
      "return20d": -0.048708,
      "sma5Distance": -0.101282,
      "sma20Distance": -0.088449,
      "emaTrend": -0.01914,
      "macdPct": -0.005127,
      "rsi14": 47.520615,
      "atr14Pct": 0.076165,
      "bollingerZ20": -1.378539,
      "realizedVol5": 0.661832,
      "realizedVol20": 0.780696,
      "downsideVol20": 0.524082,
      "maxDrawdown20": -0.193673,
      "trendEfficiency20": 0.061551,
      "volumeZScore20": -1.947482,
      "atmImpliedVol": 0.7974,
      "putCallIvSkew": -0.043976,
      "putCallVolumeRatio": 4.424242,
      "putCallOpenInterestRatio": 3.230392,
      "expectedMovePct": 0.110267,
      "meanQuoteWidthPct": 18.354785,
      "liquidContractRatio": 0.020833,
      "trendSignal": -0.79413,
      "riskAdjustedMomentum": -0.24956
    },
    {
      "symbol": "BAC",
      "historySessions": 260,
      "historyConfidence": 1,
      "return1d": -0.010809,
      "return5d": -0.014608,
      "return20d": 0.070069,
      "sma5Distance": -0.00331,
      "sma20Distance": 0.018994,
      "emaTrend": 0.024489,
      "macdPct": -0.000797,
      "rsi14": 59.271714,
      "atr14Pct": 0.018659,
      "bollingerZ20": 0.877098,
      "realizedVol5": 0.261293,
      "realizedVol20": 0.211277,
      "downsideVol20": 0.12897,
      "maxDrawdown20": -0.026711,
      "trendEfficiency20": 0.303972,
      "volumeZScore20": -2.295323,
      "atmImpliedVol": 0.311433,
      "putCallIvSkew": 0.014305,
      "putCallVolumeRatio": 0.207854,
      "putCallOpenInterestRatio": 0.486429,
      "expectedMovePct": 0.043117,
      "meanQuoteWidthPct": 35.001319,
      "liquidContractRatio": 0.5,
      "trendSignal": 0.482447,
      "riskAdjustedMomentum": 1
    },
    {
      "symbol": "COIN",
      "historySessions": 260,
      "historyConfidence": 1,
      "return1d": -0.005872,
      "return5d": -0.063564,
      "return20d": -0.014299,
      "sma5Distance": -0.009813,
      "sma20Distance": -0.005905,
      "emaTrend": -0.009514,
      "macdPct": 0.009101,
      "rsi14": 45.31739,
      "atr14Pct": 0.063755,
      "bollingerZ20": -0.121515,
      "realizedVol5": 0.241095,
      "realizedVol20": 0.589818,
      "downsideVol20": 0.296722,
      "maxDrawdown20": -0.159769,
      "trendEfficiency20": 0.025485,
      "volumeZScore20": -2.334867,
      "atmImpliedVol": 0.742598,
      "putCallIvSkew": 0.00059,
      "putCallVolumeRatio": 0.932021,
      "putCallOpenInterestRatio": 1.217701,
      "expectedMovePct": 0.102602,
      "meanQuoteWidthPct": 13.89368,
      "liquidContractRatio": 0.5,
      "trendSignal": -0.393467,
      "riskAdjustedMomentum": -0.096972
    },
    {
      "symbol": "CRM",
      "historySessions": 260,
      "historyConfidence": 1,
      "return1d": 0.046994,
      "return5d": 0.032267,
      "return20d": 0.027306,
      "sma5Distance": 0.026485,
      "sma20Distance": 0.066617,
      "emaTrend": 0.008586,
      "macdPct": 0.011086,
      "rsi14": 72.831679,
      "atr14Pct": 0.036559,
      "bollingerZ20": 1.637551,
      "realizedVol5": 0.461923,
      "realizedVol20": 0.398126,
      "downsideVol20": 0.179567,
      "maxDrawdown20": -0.098108,
      "trendEfficiency20": 0.073253,
      "volumeZScore20": -1.161321,
      "atmImpliedVol": 0.47928,
      "putCallIvSkew": 0.001747,
      "putCallVolumeRatio": 0.945804,
      "putCallOpenInterestRatio": 0.610614,
      "expectedMovePct": 0.066376,
      "meanQuoteWidthPct": 18.884391,
      "liquidContractRatio": 0.354167,
      "trendSignal": 0.402483,
      "riskAdjustedMomentum": 0.27434
    },
    {
      "symbol": "DIA",
      "historySessions": 260,
      "historyConfidence": 1,
      "return1d": -0.001265,
      "return5d": -0.009385,
      "return20d": 0.030931,
      "sma5Distance": -0.000278,
      "sma20Distance": 0.00744,
      "emaTrend": 0.008416,
      "macdPct": -0.000628,
      "rsi14": 64.376362,
      "atr14Pct": 0.010052,
      "bollingerZ20": 0.826851,
      "realizedVol5": 0.089354,
      "realizedVol20": 0.090119,
      "downsideVol20": 0.066639,
      "maxDrawdown20": -0.013809,
      "trendEfficiency20": 0.331649,
      "volumeZScore20": -2.085521,
      "atmImpliedVol": 0.120398,
      "putCallIvSkew": 0.010654,
      "putCallVolumeRatio": 1.021661,
      "putCallOpenInterestRatio": 0.509648,
      "expectedMovePct": 0.016711,
      "meanQuoteWidthPct": 9.307756,
      "liquidContractRatio": 0.479167,
      "trendSignal": 0.224708,
      "riskAdjustedMomentum": 0.824827
    },
    {
      "symbol": "GLD",
      "historySessions": 260,
      "historyConfidence": 1,
      "return1d": -0.023713,
      "return5d": -0.036794,
      "return20d": -0.047241,
      "sma5Distance": -0.018585,
      "sma20Distance": -0.027605,
      "emaTrend": -0.016264,
      "macdPct": 0.00335,
      "rsi14": 37.653205,
      "atr14Pct": 0.019491,
      "bollingerZ20": -1.124696,
      "realizedVol5": 0.197212,
      "realizedVol20": 0.238505,
      "downsideVol20": 0.156662,
      "maxDrawdown20": -0.079747,
      "trendEfficiency20": 0.2,
      "volumeZScore20": -1.656765,
      "atmImpliedVol": 0.245648,
      "putCallIvSkew": 0.016039,
      "putCallVolumeRatio": 0.337278,
      "putCallOpenInterestRatio": 0,
      "expectedMovePct": 0.038376,
      "meanQuoteWidthPct": 15.916499,
      "liquidContractRatio": 0,
      "trendSignal": -0.909023,
      "riskAdjustedMomentum": -0.792281
    },
    {
      "symbol": "HAL",
      "historySessions": 260,
      "historyConfidence": 1,
      "return1d": 0.030823,
      "return5d": 0.074242,
      "return20d": -0.1084,
      "sma5Distance": 0.026227,
      "sma20Distance": 0.014408,
      "emaTrend": -0.019306,
      "macdPct": 0.007354,
      "rsi14": 51.763236,
      "atr14Pct": 0.027287,
      "bollingerZ20": 0.292178,
      "realizedVol5": 0.38077,
      "realizedVol20": 0.355193,
      "downsideVol20": 0.224988,
      "maxDrawdown20": -0.171026,
      "trendEfficiency20": 0.331284,
      "volumeZScore20": -1.895845,
      "atmImpliedVol": 0.456291,
      "putCallIvSkew": 0.017824,
      "putCallVolumeRatio": 0.174853,
      "putCallOpenInterestRatio": 0.327654,
      "expectedMovePct": 0.063188,
      "meanQuoteWidthPct": 71.826863,
      "liquidContractRatio": 0.041667,
      "trendSignal": 0.017658,
      "riskAdjustedMomentum": -1
    },
    {
      "symbol": "INTC",
      "historySessions": 260,
      "historyConfidence": 1,
      "return1d": -0.047524,
      "return5d": -0.143862,
      "return20d": -0.105506,
      "sma5Distance": -0.044793,
      "sma20Distance": -0.156011,
      "emaTrend": -0.065837,
      "macdPct": -0.033901,
      "rsi14": 23.938002,
      "atr14Pct": 0.091856,
      "bollingerZ20": -1.84185,
      "realizedVol5": 0.748551,
      "realizedVol20": 0.899682,
      "downsideVol20": 0.570011,
      "maxDrawdown20": -0.257698,
      "trendEfficiency20": 0.107044,
      "volumeZScore20": -2.265707,
      "atmImpliedVol": 1.029882,
      "putCallIvSkew": -0.016942,
      "putCallVolumeRatio": 0.6375,
      "putCallOpenInterestRatio": 0,
      "expectedMovePct": 0.16082,
      "meanQuoteWidthPct": 40.857779,
      "liquidContractRatio": 0,
      "trendSignal": -0.755893,
      "riskAdjustedMomentum": -0.469082
    },
    {
      "symbol": "IWM",
      "historySessions": 260,
      "historyConfidence": 1,
      "return1d": -0.005237,
      "return5d": -0.014921,
      "return20d": 0.013877,
      "sma5Distance": -0.003479,
      "sma20Distance": -0.006383,
      "emaTrend": 0.002491,
      "macdPct": -0.003075,
      "rsi14": 42.774342,
      "atr14Pct": 0.015437,
      "bollingerZ20": -0.669449,
      "realizedVol5": 0.144105,
      "realizedVol20": 0.133509,
      "downsideVol20": 0.040194,
      "maxDrawdown20": -0.023199,
      "trendEfficiency20": 0.093352,
      "volumeZScore20": -2.310953,
      "atmImpliedVol": 0.188486,
      "putCallIvSkew": 0.011804,
      "putCallVolumeRatio": 2.639229,
      "putCallOpenInterestRatio": 2.243214,
      "expectedMovePct": 0.026168,
      "meanQuoteWidthPct": 2.826886,
      "liquidContractRatio": 0.875,
      "trendSignal": -0.113402,
      "riskAdjustedMomentum": 0.370051
    },
    {
      "symbol": "LRCX",
      "historySessions": 260,
      "historyConfidence": 1,
      "return1d": -0.049039,
      "return5d": -0.048686,
      "return20d": -0.081016,
      "sma5Distance": -0.017796,
      "sma20Distance": -0.106586,
      "emaTrend": -0.034782,
      "macdPct": -0.02647,
      "rsi14": 37.265363,
      "atr14Pct": 0.090474,
      "bollingerZ20": -1.393856,
      "realizedVol5": 0.833412,
      "realizedVol20": 0.969977,
      "downsideVol20": 0.605474,
      "maxDrawdown20": -0.247386,
      "trendEfficiency20": 0.076066,
      "volumeZScore20": -2.388667,
      "atmImpliedVol": 0.94564,
      "putCallIvSkew": 0.00058,
      "putCallVolumeRatio": 0.3391,
      "putCallOpenInterestRatio": 1.239222,
      "expectedMovePct": 0.130647,
      "meanQuoteWidthPct": 12.933159,
      "liquidContractRatio": 0.291667,
      "trendSignal": -0.336146,
      "riskAdjustedMomentum": -0.334095
    },
    {
      "symbol": "MS",
      "historySessions": 260,
      "historyConfidence": 1,
      "return1d": -0.011832,
      "return5d": -0.011031,
      "return20d": 0.032869,
      "sma5Distance": -0.005361,
      "sma20Distance": 0.003002,
      "emaTrend": 0.014064,
      "macdPct": -0.001929,
      "rsi14": 41.610286,
      "atr14Pct": 0.025803,
      "bollingerZ20": 0.125702,
      "realizedVol5": 0.222152,
      "realizedVol20": 0.29137,
      "downsideVol20": 0.21303,
      "maxDrawdown20": -0.079484,
      "trendEfficiency20": 0.112109,
      "volumeZScore20": -2.050269,
      "atmImpliedVol": 0.415823,
      "putCallIvSkew": 0.012549,
      "putCallVolumeRatio": 2.938202,
      "putCallOpenInterestRatio": 2.177966,
      "expectedMovePct": 0.057592,
      "meanQuoteWidthPct": 31.265912,
      "liquidContractRatio": 0.166667,
      "trendSignal": 0.118573,
      "riskAdjustedMomentum": 0.451238
    },
    {
      "symbol": "MU",
      "historySessions": 260,
      "historyConfidence": 1,
      "return1d": -0.046748,
      "return5d": -0.052023,
      "return20d": -0.062609,
      "sma5Distance": -0.025887,
      "sma20Distance": -0.11131,
      "emaTrend": -0.036026,
      "macdPct": -0.031123,
      "rsi14": 32.114633,
      "atr14Pct": 0.101178,
      "bollingerZ20": -1.323056,
      "realizedVol5": 0.628833,
      "realizedVol20": 1.124817,
      "downsideVol20": 0.69298,
      "maxDrawdown20": -0.230759,
      "trendEfficiency20": 0.05397,
      "volumeZScore20": -2.217341,
      "atmImpliedVol": 0.932119,
      "putCallIvSkew": 0.005346,
      "putCallVolumeRatio": 0.736041,
      "putCallOpenInterestRatio": 0,
      "expectedMovePct": 0.145444,
      "meanQuoteWidthPct": 11.80333,
      "liquidContractRatio": 0,
      "trendSignal": -0.264653,
      "riskAdjustedMomentum": -0.222644
    },
    {
      "symbol": "NFLX",
      "historySessions": 260,
      "historyConfidence": 1,
      "return1d": 0.022761,
      "return5d": -0.012891,
      "return20d": -0.076658,
      "sma5Distance": -0.001198,
      "sma20Distance": -0.003459,
      "emaTrend": -0.01832,
      "macdPct": 0.007317,
      "rsi14": 55.449051,
      "atr14Pct": 0.03551,
      "bollingerZ20": -0.089828,
      "realizedVol5": 0.290185,
      "realizedVol20": 0.430703,
      "downsideVol20": 0.271408,
      "maxDrawdown20": -0.131872,
      "trendEfficiency20": 0.196468,
      "volumeZScore20": -2.017152,
      "atmImpliedVol": 0.657514,
      "putCallIvSkew": -0.030719,
      "putCallVolumeRatio": 0.240244,
      "putCallOpenInterestRatio": 0.400239,
      "expectedMovePct": 0.090951,
      "meanQuoteWidthPct": 6.75526,
      "liquidContractRatio": 0.875,
      "trendSignal": -0.471747,
      "riskAdjustedMomentum": -0.711934
    },
    {
      "symbol": "NKE",
      "historySessions": 260,
      "historyConfidence": 1,
      "return1d": 0.00124,
      "return5d": 0.025035,
      "return20d": -0.033399,
      "sma5Distance": 0.020443,
      "sma20Distance": 0.028005,
      "emaTrend": 0.009057,
      "macdPct": 0.005782,
      "rsi14": 56.435649,
      "atr14Pct": 0.032414,
      "bollingerZ20": 0.826112,
      "realizedVol5": 0.284178,
      "realizedVol20": 0.354168,
      "downsideVol20": 0.189721,
      "maxDrawdown20": -0.113359,
      "trendEfficiency20": 0.102847,
      "volumeZScore20": -1.381969,
      "atmImpliedVol": 0.362393,
      "putCallIvSkew": 0.00624,
      "putCallVolumeRatio": 1.069682,
      "putCallOpenInterestRatio": 0.732409,
      "expectedMovePct": 0.050197,
      "meanQuoteWidthPct": 37.880939,
      "liquidContractRatio": 0.333333,
      "trendSignal": 0.024821,
      "riskAdjustedMomentum": -0.377206
    },
    {
      "symbol": "NOW",
      "historySessions": 260,
      "historyConfidence": 1,
      "return1d": 0.034723,
      "return5d": 0.032614,
      "return20d": 0.081199,
      "sma5Distance": 0.019652,
      "sma20Distance": 0.095563,
      "emaTrend": 0.037642,
      "macdPct": 0.011209,
      "rsi14": 72.586955,
      "atr14Pct": 0.049552,
      "bollingerZ20": 1.49204,
      "realizedVol5": 0.400728,
      "realizedVol20": 0.573307,
      "downsideVol20": 0.283701,
      "maxDrawdown20": -0.140471,
      "trendEfficiency20": 0.152487,
      "volumeZScore20": -2.234758,
      "atmImpliedVol": 0.926059,
      "putCallIvSkew": -0.004107,
      "putCallVolumeRatio": 0.210233,
      "putCallOpenInterestRatio": 0.274378,
      "expectedMovePct": 0.12786,
      "meanQuoteWidthPct": 6.82687,
      "liquidContractRatio": 0.75,
      "trendSignal": 0.480391,
      "riskAdjustedMomentum": 0.566531
    },
    {
      "symbol": "NVDA",
      "historySessions": 260,
      "historyConfidence": 1,
      "return1d": -0.018866,
      "return5d": 0.058451,
      "return20d": 0.010299,
      "sma5Distance": 0.01285,
      "sma20Distance": 0.024364,
      "emaTrend": 0.008544,
      "macdPct": 0.006891,
      "rsi14": 48.385855,
      "atr14Pct": 0.032064,
      "bollingerZ20": 0.800526,
      "realizedVol5": 0.409372,
      "realizedVol20": 0.359742,
      "downsideVol20": 0.160515,
      "maxDrawdown20": -0.093763,
      "trendEfficiency20": 0.028062,
      "volumeZScore20": -2.827558,
      "atmImpliedVol": 0.386772,
      "putCallIvSkew": 0.012629,
      "putCallVolumeRatio": 0.643875,
      "putCallOpenInterestRatio": 0,
      "expectedMovePct": 0.060755,
      "meanQuoteWidthPct": 50.457999,
      "liquidContractRatio": 0,
      "trendSignal": 0.576451,
      "riskAdjustedMomentum": 0.114518
    },
    {
      "symbol": "ON",
      "historySessions": 260,
      "historyConfidence": 1,
      "return1d": -0.046269,
      "return5d": -0.033478,
      "return20d": -0.210762,
      "sma5Distance": -0.02688,
      "sma20Distance": -0.12967,
      "emaTrend": -0.074885,
      "macdPct": -0.013801,
      "rsi14": 24.54534,
      "atr14Pct": 0.094071,
      "bollingerZ20": -0.955852,
      "realizedVol5": 0.642611,
      "realizedVol20": 1.273111,
      "downsideVol20": 1.22351,
      "maxDrawdown20": -0.32672,
      "trendEfficiency20": 0.203362,
      "volumeZScore20": -1.3689,
      "atmImpliedVol": 0.906079,
      "putCallIvSkew": -0.019953,
      "putCallVolumeRatio": 0.234218,
      "putCallOpenInterestRatio": 3.66311,
      "expectedMovePct": 0.125656,
      "meanQuoteWidthPct": 18.000621,
      "liquidContractRatio": 0.270833,
      "trendSignal": -0.433889,
      "riskAdjustedMomentum": -0.662196
    },
    {
      "symbol": "ORCL",
      "historySessions": 260,
      "historyConfidence": 1,
      "return1d": -0.037614,
      "return5d": -0.0585,
      "return20d": -0.264802,
      "sma5Distance": -0.03638,
      "sma20Distance": -0.141945,
      "emaTrend": -0.105083,
      "macdPct": -0.008164,
      "rsi14": 13.330851,
      "atr14Pct": 0.054249,
      "bollingerZ20": -1.151752,
      "realizedVol5": 0.384997,
      "realizedVol20": 0.420584,
      "downsideVol20": 0.255573,
      "maxDrawdown20": -0.297394,
      "trendEfficiency20": 0.596039,
      "volumeZScore20": -1.82311,
      "atmImpliedVol": 0.61315,
      "putCallIvSkew": -0.0088,
      "putCallVolumeRatio": 0.778664,
      "putCallOpenInterestRatio": 1.520492,
      "expectedMovePct": 0.08478,
      "meanQuoteWidthPct": 5.70816,
      "liquidContractRatio": 0.541667,
      "trendSignal": -1,
      "riskAdjustedMomentum": -1
    },
    {
      "symbol": "OXY",
      "historySessions": 260,
      "historyConfidence": 1,
      "return1d": 0.015126,
      "return5d": 0.099979,
      "return20d": -0.032089,
      "sma5Distance": 0.016279,
      "sma20Distance": 0.038974,
      "emaTrend": 0.003973,
      "macdPct": 0.010981,
      "rsi14": 56.358165,
      "atr14Pct": 0.027811,
      "bollingerZ20": 0.892177,
      "realizedVol5": 0.483482,
      "realizedVol20": 0.368934,
      "downsideVol20": 0.149202,
      "maxDrawdown20": -0.152105,
      "trendEfficiency20": 0.09242,
      "volumeZScore20": -1.611357,
      "atmImpliedVol": 0.368162,
      "putCallIvSkew": -0.003832,
      "putCallVolumeRatio": 0.105424,
      "putCallOpenInterestRatio": 0.881413,
      "expectedMovePct": 0.05122,
      "meanQuoteWidthPct": 54.606336,
      "liquidContractRatio": 0.3125,
      "trendSignal": 0.676284,
      "riskAdjustedMomentum": -0.347915
    },
    {
      "symbol": "PFE",
      "historySessions": 260,
      "historyConfidence": 1,
      "return1d": 0.016756,
      "return5d": 0.036046,
      "return20d": -0.060948,
      "sma5Distance": 0.014532,
      "sma20Distance": -0.002365,
      "emaTrend": -0.011702,
      "macdPct": 0.002196,
      "rsi14": 44.621944,
      "atr14Pct": 0.023628,
      "bollingerZ20": -0.070904,
      "realizedVol5": 0.142008,
      "realizedVol20": 0.239902,
      "downsideVol20": 0.152279,
      "maxDrawdown20": -0.09691,
      "trendEfficiency20": 0.268292,
      "volumeZScore20": -1.617068,
      "atmImpliedVol": 0.274021,
      "putCallIvSkew": 0.101447,
      "putCallVolumeRatio": 0.634358,
      "putCallOpenInterestRatio": 0.768308,
      "expectedMovePct": 0.038047,
      "meanQuoteWidthPct": 83.385208,
      "liquidContractRatio": 0.229167,
      "trendSignal": -0.060695,
      "riskAdjustedMomentum": -1
    },
    {
      "symbol": "PLTR",
      "historySessions": 260,
      "historyConfidence": 1,
      "return1d": 0.013802,
      "return5d": -0.03018,
      "return20d": -0.019377,
      "sma5Distance": -0.012689,
      "sma20Distance": 0.03003,
      "emaTrend": 0.008042,
      "macdPct": 0.011698,
      "rsi14": 59.288945,
      "atr14Pct": 0.053407,
      "bollingerZ20": 0.451434,
      "realizedVol5": 0.291676,
      "realizedVol20": 0.58212,
      "downsideVol20": 0.299696,
      "maxDrawdown20": -0.203697,
      "trendEfficiency20": 0.034473,
      "volumeZScore20": -2.475566,
      "atmImpliedVol": 0.541446,
      "putCallIvSkew": 0.014722,
      "putCallVolumeRatio": 0.640447,
      "putCallOpenInterestRatio": 0.638508,
      "expectedMovePct": 0.075074,
      "meanQuoteWidthPct": 4.721602,
      "liquidContractRatio": 0.9375,
      "trendSignal": -0.235057,
      "riskAdjustedMomentum": -0.133151
    },
    {
      "symbol": "QQQ",
      "historySessions": 260,
      "historyConfidence": 1,
      "return1d": -0.012253,
      "return5d": -0.008578,
      "return20d": -0.000697,
      "sma5Distance": -0.000887,
      "sma20Distance": -0.008193,
      "emaTrend": -0.000722,
      "macdPct": -0.001775,
      "rsi14": 42.655467,
      "atr14Pct": 0.021727,
      "bollingerZ20": -0.545787,
      "realizedVol5": 0.221207,
      "realizedVol20": 0.27992,
      "downsideVol20": 0.13556,
      "maxDrawdown20": -0.050376,
      "trendEfficiency20": 0.002333,
      "volumeZScore20": -2.798377,
      "atmImpliedVol": 0.231371,
      "putCallIvSkew": -0.003222,
      "putCallVolumeRatio": 0.980916,
      "putCallOpenInterestRatio": 2.103846,
      "expectedMovePct": 0.032039,
      "meanQuoteWidthPct": 1.140063,
      "liquidContractRatio": 1,
      "trendSignal": -0.10256,
      "riskAdjustedMomentum": -0.009963
    },
    {
      "symbol": "SLV",
      "historySessions": 260,
      "historyConfidence": 1,
      "return1d": -0.027062,
      "return5d": -0.064516,
      "return20d": -0.136962,
      "sma5Distance": -0.020234,
      "sma20Distance": -0.061891,
      "emaTrend": -0.046104,
      "macdPct": 0.005059,
      "rsi14": 33.015869,
      "atr14Pct": 0.041722,
      "bollingerZ20": -0.909301,
      "realizedVol5": 0.379805,
      "realizedVol20": 0.463243,
      "downsideVol20": 0.359402,
      "maxDrawdown20": -0.184182,
      "trendEfficiency20": 0.319035,
      "volumeZScore20": -1.392815,
      "atmImpliedVol": 0.438429,
      "putCallIvSkew": 0.045695,
      "putCallVolumeRatio": 0.716535,
      "putCallOpenInterestRatio": 0,
      "expectedMovePct": 0.06868,
      "meanQuoteWidthPct": 23.272829,
      "liquidContractRatio": 0,
      "trendSignal": -1,
      "riskAdjustedMomentum": -1
    },
    {
      "symbol": "SMH",
      "historySessions": 260,
      "historyConfidence": 1,
      "return1d": -0.027478,
      "return5d": -0.016647,
      "return20d": -0.024957,
      "sma5Distance": -0.005439,
      "sma20Distance": -0.042911,
      "emaTrend": -0.012175,
      "macdPct": -0.010142,
      "rsi14": 36.776124,
      "atr14Pct": 0.049791,
      "bollingerZ20": -1.125336,
      "realizedVol5": 0.450679,
      "realizedVol20": 0.599963,
      "downsideVol20": 0.31599,
      "maxDrawdown20": -0.13075,
      "trendEfficiency20": 0.037649,
      "volumeZScore20": -2.084274,
      "atmImpliedVol": 0.532079,
      "putCallIvSkew": 0.018207,
      "putCallVolumeRatio": 3.25,
      "putCallOpenInterestRatio": 0,
      "expectedMovePct": 0.083089,
      "meanQuoteWidthPct": 21.277209,
      "liquidContractRatio": 0,
      "trendSignal": -0.17614,
      "riskAdjustedMomentum": -0.16639
    },
    {
      "symbol": "SPY",
      "historySessions": 260,
      "historyConfidence": 1,
      "return1d": -0.003702,
      "return5d": 0.001165,
      "return20d": 0.019512,
      "sma5Distance": 0.002359,
      "sma20Distance": 0.01024,
      "emaTrend": 0.007096,
      "macdPct": 0.001214,
      "rsi14": 56.260566,
      "atr14Pct": 0.012094,
      "bollingerZ20": 1.024376,
      "realizedVol5": 0.092327,
      "realizedVol20": 0.135816,
      "downsideVol20": 0.072964,
      "maxDrawdown20": -0.034233,
      "trendEfficiency20": 0.142405,
      "volumeZScore20": -2.741862,
      "atmImpliedVol": 0.122147,
      "putCallIvSkew": 0.005808,
      "putCallVolumeRatio": 1.362525,
      "putCallOpenInterestRatio": 0.268309,
      "expectedMovePct": 0.016951,
      "meanQuoteWidthPct": 1.224324,
      "liquidContractRatio": 0.958333,
      "trendSignal": 0.283449,
      "riskAdjustedMomentum": 0.520313
    },
    {
      "symbol": "TLT",
      "historySessions": 260,
      "historyConfidence": 1,
      "return1d": -0.003492,
      "return5d": -0.014921,
      "return20d": -0.020993,
      "sma5Distance": -0.002772,
      "sma20Distance": -0.019816,
      "emaTrend": -0.00999,
      "macdPct": -0.00339,
      "rsi14": 30.676081,
      "atr14Pct": 0.006708,
      "bollingerZ20": -1.583083,
      "realizedVol5": 0.07388,
      "realizedVol20": 0.094142,
      "downsideVol20": 0.072644,
      "maxDrawdown20": -0.03745,
      "trendEfficiency20": 0.261405,
      "volumeZScore20": -2.440849,
      "atmImpliedVol": 0.090076,
      "putCallIvSkew": 0.007375,
      "putCallVolumeRatio": 15.904762,
      "putCallOpenInterestRatio": 0,
      "expectedMovePct": 0.014375,
      "meanQuoteWidthPct": 58.440082,
      "liquidContractRatio": 0,
      "trendSignal": -0.57833,
      "riskAdjustedMomentum": -0.559821
    },
    {
      "symbol": "TSLA",
      "historySessions": 260,
      "historyConfidence": 1,
      "return1d": -0.020846,
      "return5d": -0.04886,
      "return20d": 0.000276,
      "sma5Distance": -0.007078,
      "sma20Distance": -0.004044,
      "emaTrend": -0.000123,
      "macdPct": 0.001675,
      "rsi14": 48.44514,
      "atr14Pct": 0.049667,
      "bollingerZ20": -0.112224,
      "realizedVol5": 0.441863,
      "realizedVol20": 0.591207,
      "downsideVol20": 0.386406,
      "maxDrawdown20": -0.087632,
      "trendEfficiency20": 0.000496,
      "volumeZScore20": -2.430608,
      "atmImpliedVol": 0.525123,
      "putCallIvSkew": 0.025432,
      "putCallVolumeRatio": 0.981481,
      "putCallOpenInterestRatio": 0,
      "expectedMovePct": 0.082027,
      "meanQuoteWidthPct": 21.446498,
      "liquidContractRatio": 0,
      "trendSignal": -0.261402,
      "riskAdjustedMomentum": 0.001865
    },
    {
      "symbol": "TXN",
      "historySessions": 260,
      "historyConfidence": 1,
      "return1d": -0.026617,
      "return5d": -0.001087,
      "return20d": 0.020431,
      "sma5Distance": -0.001272,
      "sma20Distance": -0.002438,
      "emaTrend": 0.0086,
      "macdPct": 0.000004,
      "rsi14": 38.771897,
      "atr14Pct": 0.051584,
      "bollingerZ20": -0.066035,
      "realizedVol5": 0.454052,
      "realizedVol20": 0.639843,
      "downsideVol20": 0.520178,
      "maxDrawdown20": -0.140996,
      "trendEfficiency20": 0.032334,
      "volumeZScore20": -1.322036,
      "atmImpliedVol": 0.882101,
      "putCallIvSkew": 0.010676,
      "putCallVolumeRatio": 1.668675,
      "putCallOpenInterestRatio": 0.434343,
      "expectedMovePct": 0.121879,
      "meanQuoteWidthPct": 16.817346,
      "liquidContractRatio": 0.125,
      "trendSignal": 0.06219,
      "riskAdjustedMomentum": 0.127724
    },
    {
      "symbol": "USO",
      "historySessions": 260,
      "historyConfidence": 1,
      "return1d": 0.040938,
      "return5d": 0.084332,
      "return20d": -0.121711,
      "sma5Distance": 0.024928,
      "sma20Distance": 0.022432,
      "emaTrend": -0.024859,
      "macdPct": 0.011253,
      "rsi14": 50.646791,
      "atr14Pct": 0.032906,
      "bollingerZ20": 0.433476,
      "realizedVol5": 0.493567,
      "realizedVol20": 0.440583,
      "downsideVol20": 0.237548,
      "maxDrawdown20": -0.198401,
      "trendEfficiency20": 0.295961,
      "volumeZScore20": -0.57713,
      "atmImpliedVol": 0.528654,
      "putCallIvSkew": -0.007467,
      "putCallVolumeRatio": 0.442698,
      "putCallOpenInterestRatio": 1.101967,
      "expectedMovePct": 0.073133,
      "meanQuoteWidthPct": 27.97933,
      "liquidContractRatio": 0.520833,
      "trendSignal": 0.022995,
      "riskAdjustedMomentum": -1
    },
    {
      "symbol": "WFC",
      "historySessions": 260,
      "historyConfidence": 1,
      "return1d": -0.007113,
      "return5d": -0.010406,
      "return20d": 0.050243,
      "sma5Distance": -0.0015,
      "sma20Distance": 0.019797,
      "emaTrend": 0.021838,
      "macdPct": 0.000593,
      "rsi14": 60.563389,
      "atr14Pct": 0.020129,
      "bollingerZ20": 1.050583,
      "realizedVol5": 0.201395,
      "realizedVol20": 0.249431,
      "downsideVol20": 0.093247,
      "maxDrawdown20": -0.03351,
      "trendEfficiency20": 0.196208,
      "volumeZScore20": -1.719566,
      "atmImpliedVol": 0.419106,
      "putCallIvSkew": 0.019266,
      "putCallVolumeRatio": 4.341232,
      "putCallOpenInterestRatio": 0.468612,
      "expectedMovePct": 0.058239,
      "meanQuoteWidthPct": 33.228079,
      "liquidContractRatio": 0.25,
      "trendSignal": 0.293893,
      "riskAdjustedMomentum": 0.805717
    },
    {
      "symbol": "XLE",
      "historySessions": 260,
      "historyConfidence": 1,
      "return1d": 0.022603,
      "return5d": 0.060135,
      "return20d": -0.013918,
      "sma5Distance": 0.018664,
      "sma20Distance": 0.034212,
      "emaTrend": 0.004859,
      "macdPct": 0.006578,
      "rsi14": 63.571004,
      "atr14Pct": 0.018174,
      "bollingerZ20": 1.549037,
      "realizedVol5": 0.266611,
      "realizedVol20": 0.236519,
      "downsideVol20": 0.152449,
      "maxDrawdown20": -0.082363,
      "trendEfficiency20": 0.061892,
      "volumeZScore20": -1.879031,
      "atmImpliedVol": 0.259157,
      "putCallIvSkew": 0.000435,
      "putCallVolumeRatio": 0.076133,
      "putCallOpenInterestRatio": 0.798324,
      "expectedMovePct": 0.035952,
      "meanQuoteWidthPct": 25.325655,
      "liquidContractRatio": 0.229167,
      "trendSignal": 0.682674,
      "riskAdjustedMomentum": -0.235382
    },
    {
      "symbol": "XLF",
      "historySessions": 260,
      "historyConfidence": 1,
      "return1d": 0.000449,
      "return5d": -0.007214,
      "return20d": 0.059198,
      "sma5Distance": 0.00241,
      "sma20Distance": 0.023539,
      "emaTrend": 0.019666,
      "macdPct": 0.001561,
      "rsi14": 68.652614,
      "atr14Pct": 0.013146,
      "bollingerZ20": 1.281993,
      "realizedVol5": 0.175089,
      "realizedVol20": 0.150624,
      "downsideVol20": 0.098924,
      "maxDrawdown20": -0.020841,
      "trendEfficiency20": 0.384806,
      "volumeZScore20": -2.305879,
      "atmImpliedVol": 0.155734,
      "putCallIvSkew": 0.03946,
      "putCallVolumeRatio": 0,
      "putCallOpenInterestRatio": 0,
      "expectedMovePct": 0.024491,
      "meanQuoteWidthPct": 107.337178,
      "liquidContractRatio": 0,
      "trendSignal": 0.645025,
      "riskAdjustedMomentum": 1
    },
    {
      "symbol": "XLK",
      "historySessions": 260,
      "historyConfidence": 1,
      "return1d": -0.015179,
      "return5d": -0.003323,
      "return20d": -0.001365,
      "sma5Distance": 0.000142,
      "sma20Distance": -0.012554,
      "emaTrend": -0.001969,
      "macdPct": -0.003527,
      "rsi14": 40.848451,
      "atr14Pct": 0.031023,
      "bollingerZ20": -0.624196,
      "realizedVol5": 0.301058,
      "realizedVol20": 0.361634,
      "downsideVol20": 0.19015,
      "maxDrawdown20": -0.067499,
      "trendEfficiency20": 0.003515,
      "volumeZScore20": -2.676303,
      "atmImpliedVol": 0.364223,
      "putCallIvSkew": 0.030863,
      "putCallVolumeRatio": 0.484424,
      "putCallOpenInterestRatio": 0.879953,
      "expectedMovePct": 0.050421,
      "meanQuoteWidthPct": 26.040419,
      "liquidContractRatio": 0.25,
      "trendSignal": -0.037161,
      "riskAdjustedMomentum": -0.015094
    },
    {
      "symbol": "XOM",
      "historySessions": 260,
      "historyConfidence": 1,
      "return1d": 0.029882,
      "return5d": 0.0483,
      "return20d": -0.024352,
      "sma5Distance": 0.018457,
      "sma20Distance": 0.028138,
      "emaTrend": -0.002907,
      "macdPct": 0.006071,
      "rsi14": 59.563757,
      "atr14Pct": 0.019982,
      "bollingerZ20": 1.36866,
      "realizedVol5": 0.409602,
      "realizedVol20": 0.285121,
      "downsideVol20": 0.207528,
      "maxDrawdown20": -0.074485,
      "trendEfficiency20": 0.099194,
      "volumeZScore20": -1.503002,
      "atmImpliedVol": 0.290858,
      "putCallIvSkew": -0.007808,
      "putCallVolumeRatio": 0.259218,
      "putCallOpenInterestRatio": 0.31506,
      "expectedMovePct": 0.040271,
      "meanQuoteWidthPct": 24.852305,
      "liquidContractRatio": 0.3125,
      "trendSignal": 0.357052,
      "riskAdjustedMomentum": -0.341638
    }
  ]
}
